picklejar3/__init__.py
picklejar3/picklejar.py
picklejar3-0.2.0.dist-info/LICENSE
picklejar3-0.2.0.dist-info/WHEEL
picklejar3-0.2.0.dist-info/METADATA
picklejar3-0.2.0.dist-info/RECORD
